{
  "id": "PwHuwmxZuYA",
  "date_time": 1757163984,
  "is_live": true,
  "platform_type": "youtube",
  "url": "https://www.youtube.com/watch?utm_campaign=hp_holodule\u0026utm_medium=social\u0026utm_source=holoplus\u0026v=PwHuwmxZuYA",
  "thumbnail": "https://img.youtube.com/vi/PwHuwmxZuYA/mqdefault.jpg",
  "title": "【 グッドピザ、グレートピザ 】復活！熱血ピザ屋ドドドピザ！！！【角巻わため/ホロライブ４期生】",
  "reaction_total": 0,
  "streamer": {
    "id": "",
    "name": "Tsunomaki Watame",
    "image_url": "https://yt3.ggpht.com/XJYar8ZAQ59ce0nFlf-Dl6V16Dwznu5xfh3XnMW_JE-nCVLHLiRTS-x1gB_eR4_CJY3KDfKxsVo=s88-c-k-c0x00ffffff-no-rj",
    "created_at": null,
    "updated_at": null
  },
  "talents": [
    {
      "id": "c5a07d80-0d02-4167-89e2-06faeed5bcab",
      "name": "Tsunomaki Watame",
      "key_name": "tsunomaki_watame",
      "img_url": "https://asset.holoplus.com/talents/hololive/tsunomaki_watame/icon.png",
      "created_at": -62135596800,
      "updated_at": -62135596800,
      "deleted_at": null,
      "group_id": "e9171551-cb2a-483e-8a77-fdffba8e632b"
    }
  ],
  "created_at": 0,
  "updated_at": 0
}
